pycov_convert_relative_filenames/__init__.py
pycov_convert_relative_filenames/__main__.py
pycov_convert_relative_filenames-1.1.1.dist-info/LICENSE
pycov_convert_relative_filenames-1.1.1.dist-info/METADATA
pycov_convert_relative_filenames-1.1.1.dist-info/WHEEL
pycov_convert_relative_filenames-1.1.1.dist-info/entry_points.txt
pycov_convert_relative_filenames-1.1.1.dist-info/top_level.txt
pycov_convert_relative_filenames-1.1.1.dist-info/zip-safe
pycov_convert_relative_filenames-1.1.1.dist-info/RECORD
