Metadata-Version: 2.1
Name: pycov-convert-relative-filenames
Version: 1.1.1
Summary: A quick and dirty helper script to convert a xml coverage report
Author-email: Julien Lecomte <julien@lecomte.at>
License: MIT
Project-URL: Homepage, https://gitlab.com/jlecomte/projects/python/pycov-convert-relative-filenames
Project-URL: Documentation, https://gitlab.com/jlecomte/projects/python/pycov-convert-relative-filenames/-/blob/master/README.md
Project-URL: Source code, https://gitlab.com/jlecomte/projects/python/pycov-convert-relative-filenames
Project-URL: Bug tracker, https://gitlab.com/jlecomte/projects/python/pycov-convert-relative-filenames/-/issues
Classifier: License :: OSI Approved :: MIT License
Classifier: Intended Audience :: Developers
Classifier: Topic :: Software Development :: Quality Assurance
Classifier: Development Status :: 5 - Production/Stable
Classifier: Programming Language :: Python :: 3 :: Only
Classifier: Programming Language :: Python :: 3.6
Classifier: Programming Language :: Python :: 3.7
Classifier: Programming Language :: Python :: 3.8
Classifier: Programming Language :: Python :: 3.9
Requires-Python: >=3.6
License-File: LICENSE
